<?xml version="1.0" encoding="utf-8" ?>
<dwsync>
<file name="icons.png" local="129984903620000000" remote="129984900290000000" testing="129984900290000000" />
<file name="dialog.css" local="129984903620000000" remote="129984900290000000" testing="129984900290000000" />
<file name="dialog_ie.css" local="129984903620000000" remote="129984900290000000" testing="129984900290000000" />
<file name="dialog_ie7.css" local="129984903620000000" remote="129984900290000000" testing="129984900290000000" />
<file name="dialog_ie8.css" local="129984903620000000" remote="129984900290000000" testing="129984900290000000" />
<file name="dialog_opera.css" local="129984903620000000" remote="129984900290000000" testing="129984900290000000" />
<file name="editor.css" local="129984903620000000" remote="129984900290000000" testing="129984900290000000" />
<file name="editor_gecko.css" local="129984903620000000" remote="129984900290000000" testing="129984900290000000" />
<file name="editor_ie.css" local="129984903620000000" remote="129984900290000000" testing="129984900290000000" />
<file name="editor_ie7.css" local="129984903620000000" remote="129984900290000000" testing="129984900290000000" />
<file name="editor_ie8.css" local="129984903620000000" remote="129984900290000000" testing="129984900290000000" />
<file name="readme.md" local="129984903620000000" remote="129984900290000000" testing="129984900290000000" />
</dwsync>